{
    "publication": "karl",
    "series": 1,
    "episode": 157,
    "name": "Interview - The Balance Podcast",
    "summary": "",
    "version": "0.0.0",
    "release_date": "2020-01-05T00:00:00Z",
    "incomplete": false,
    "bestof": false,
    "special": false,
    "locked": true,
    "offset_accuracy": 0,
    "audio_quality": "",
    "metadata": {
      "cover_art_url": "/assets/cover/default.jpg",
      "duration_ms": "4018000"
    },
    "transcript": [],
    "synopsis": null,
    "contributors": null,
    "trivia": null
  }
